ReactNativeZhongwenWendang/README.md
ReactNativeZhongwenWendang/__init__.py
ReactNativeZhongwenWendang/__main__.py
ReactNativeZhongwenWendang/file.epub
ReactNativeZhongwenWendang/index.html
ReactNativeZhongwenWendang/css/__init__.py
ReactNativeZhongwenWendang/css/annotations.css
ReactNativeZhongwenWendang/css/main.css
ReactNativeZhongwenWendang/css/normalize.css
ReactNativeZhongwenWendang/css/popup.css
ReactNativeZhongwenWendang/font/__init__.py
ReactNativeZhongwenWendang/font/fontello.eot
ReactNativeZhongwenWendang/font/fontello.svg
ReactNativeZhongwenWendang/font/fontello.ttf
ReactNativeZhongwenWendang/font/fontello.woff
ReactNativeZhongwenWendang/img/__init__.py
ReactNativeZhongwenWendang/img/annotator-glyph-sprite.png
ReactNativeZhongwenWendang/img/annotator-icon-sprite.png
ReactNativeZhongwenWendang/img/apple-touch-icon.png
ReactNativeZhongwenWendang/img/cancelfullscreen.png
ReactNativeZhongwenWendang/img/close.png
ReactNativeZhongwenWendang/img/fullscreen.png
ReactNativeZhongwenWendang/img/loader.gif
ReactNativeZhongwenWendang/img/menu-icon.png
ReactNativeZhongwenWendang/img/save.png
ReactNativeZhongwenWendang/img/saved.png
ReactNativeZhongwenWendang/img/settings-s.png
ReactNativeZhongwenWendang/img/settings.png
ReactNativeZhongwenWendang/img/star.png
ReactNativeZhongwenWendang/js/__init__.py
ReactNativeZhongwenWendang/js/epub.js
ReactNativeZhongwenWendang/js/epub.min.js
ReactNativeZhongwenWendang/js/epub.min.map
ReactNativeZhongwenWendang/js/hooks.min.js
ReactNativeZhongwenWendang/js/hooks.min.map
ReactNativeZhongwenWendang/js/reader.js
ReactNativeZhongwenWendang/js/reader.js.map
ReactNativeZhongwenWendang/js/reader.min.js
ReactNativeZhongwenWendang/js/reader.min.map
ReactNativeZhongwenWendang/js/hooks/__init__.py
ReactNativeZhongwenWendang/js/hooks/extensions/__init__.py
ReactNativeZhongwenWendang/js/hooks/extensions/highlight.js
ReactNativeZhongwenWendang/js/libs/__init__.py
ReactNativeZhongwenWendang/js/libs/jquery.min.js
react_native_zhongwen_wendang-2024.3.1.0.dist-info/METADATA
react_native_zhongwen_wendang-2024.3.1.0.dist-info/WHEEL
react_native_zhongwen_wendang-2024.3.1.0.dist-info/entry_points.txt
react_native_zhongwen_wendang-2024.3.1.0.dist-info/top_level.txt
react_native_zhongwen_wendang-2024.3.1.0.dist-info/RECORD
